solutions_builder/__init__.py
solutions_builder/cli/__init__.py
solutions_builder/cli/add.py
solutions_builder/cli/cli.py
solutions_builder/cli/cli_constants.py
solutions_builder/cli/cli_utils.py
solutions_builder/cli/component.py
solutions_builder/cli/infra.py
solutions_builder/cli/list.py
solutions_builder/cli/replay.py
solutions_builder/cli/set.py
solutions_builder/cli/template.py
solutions_builder/cli/update.py
solutions_builder/cli/vars.py
solutions_builder/cli/vars_test.py
solutions_builder/copier_extensions/__init__.py
solutions_builder/copier_extensions/context.py
solutions_builder/copier_extensions/sb_helpers.py
solutions_builder/downloaded_repos/git@gitlab.com:google-cloud-ce/communities/NATT-AIML/genai-fsa/northam/experimental/sb-templates.git/.git/HEAD
solutions_builder/downloaded_repos/git@gitlab.com:google-cloud-ce/communities/NATT-AIML/genai-fsa/northam/experimental/sb-templates.git/.git/config
solutions_builder/downloaded_repos/git@gitlab.com:google-cloud-ce/communities/NATT-AIML/genai-fsa/northam/experimental/sb-templates.git/.git/description
solutions_builder/downloaded_repos/git@gitlab.com:google-cloud-ce/communities/NATT-AIML/genai-fsa/northam/experimental/sb-templates.git/.git/hooks/applypatch-msg.sample
solutions_builder/downloaded_repos/git@gitlab.com:google-cloud-ce/communities/NATT-AIML/genai-fsa/northam/experimental/sb-templates.git/.git/hooks/commit-msg.sample
solutions_builder/downloaded_repos/git@gitlab.com:google-cloud-ce/communities/NATT-AIML/genai-fsa/northam/experimental/sb-templates.git/.git/hooks/fsmonitor-watchman.sample
solutions_builder/downloaded_repos/git@gitlab.com:google-cloud-ce/communities/NATT-AIML/genai-fsa/northam/experimental/sb-templates.git/.git/hooks/post-update.sample
solutions_builder/downloaded_repos/git@gitlab.com:google-cloud-ce/communities/NATT-AIML/genai-fsa/northam/experimental/sb-templates.git/.git/hooks/pre-applypatch.sample
solutions_builder-2.0.0.dist-info/LICENSE
solutions_builder-2.0.0.dist-info/METADATA
solutions_builder-2.0.0.dist-info/WHEEL
solutions_builder-2.0.0.dist-info/entry_points.txt
solutions_builder-2.0.0.dist-info/RECORD
