Metadata-Version: 2.1
Name: solutions-builder
Version: 2.0.0
Summary: A solution framework to generate a project with built-in structure and modules
Home-page: https://github.com/GoogleCloudPlatform/solutions-builder
License: Apache
Author: Jon Chen
Author-email: jonchen@google.com
Requires-Python: >=3.9,<4.0
Classifier: License :: Other/Proprietary License
Classifier: Programming Language :: Python :: 3
Classifier: Programming Language :: Python :: 3.9
Classifier: Programming Language :: Python :: 3.10
Classifier: Programming Language :: Python :: 3.11
Classifier: Programming Language :: Python :: 3.12
Requires-Dist: copier (>=9.2.0)
Requires-Dist: copier-templates-extensions (>=0.3.0,<0.4.0)
Requires-Dist: gitpython (>=3.1.43,<4.0.0)
Requires-Dist: jinja2 (>=3.1.2,<4.0.0)
Requires-Dist: jinja2-strcase (>=0.0.2,<0.0.3)
Requires-Dist: jinja2-time (>=0.2.0,<0.3.0)
Requires-Dist: pathlib (>=1.0.1,<2.0.0)
Requires-Dist: pydantic (>=2)
Requires-Dist: pyyaml (>=6.0,<7.0)
Requires-Dist: typer (>=0.9.0)
Project-URL: Repository, https://github.com/GoogleCloudPlatform/solutions-builder
